Metadata-Version: 1.0
Name: Raghav-Chhabra-Proprietary
Version: 0.1
Summary: Gaussian distributions
Home-page: UNKNOWN
Author: Shagoon Malhotra
Author-email: shagoon2895@gmail.com
License: UNKNOWN
Platform: UNKNOWN
